{"cameraMode":{"drawMode":0,"name":"Shaded","section":"Shading Mode"},"sceneLighting":true,"audioPlay":false,"sceneViewState":{"m_AlwaysRefresh":false,"showFog":true,"showSkybox":true,"showFlares":true,"showImageEffects":true,"showParticleSystems":true,"showVisualEffectGraphs":true,"m_FxEnabled":true},"in2DMode":false,"pivot":{"x":4.611377716064453,"y":0.5308303833007813,"z":15.19517993927002},"rotation":{"x":-0.1500309705734253,"y":0.6848451495170593,"z":-0.1472657024860382,"w":-0.6977041959762573},"size":13.73136043548584,"orthographic":false}